{
    "nodes": [
      {
        "id": "0",
        "name": "Place",
        "symbolSize": 65,
        "value": 100,
        "category": 0
      },
      {
        "id": "1",
        "name": "political",
        "symbolSize": 35,
        "value": 61.600006,
        "category": 1
      },
      {
        "id": "2",
        "name": "route",
        "symbolSize": 35,
        "value": 9.485714,
        "category": 1
      },
      {
        "id": "3",
        "name": "intersection",
        "symbolSize": 35,
        "value": 9.485714,
        "category": 1
      },
      {
        "id": "4",
        "name": "administrative_area",
        "symbolSize": 35,
        "value": 4,
        "category": 1
      },
      {
        "id": "5",
        "name": "administrative_area_1",
        "symbolSize": 20,
        "value": 4,
        "category": 1
      },
      {
        "id": "6",
        "name": "administrative_area_2",
        "symbolSize": 20,
        "value": 4,
        "category": 1
      },
      {
        "id": "7",
        "name": "administrative_area_3",
        "symbolSize": 20,
        "value": 4,
        "category": 1
      },
      {
        "id": "8",
        "name": "administrative_area_4",
        "symbolSize": 20,
        "value": 4,
        "category": 1
      },
      {
        "id": "9",
        "name": "administrative_area_5",
        "symbolSize": 20,
        "value": 4,
        "category": 1
      },
      {
        "id": "10",
        "name": "colloquial_area",
        "symbolSize": 35,
        "value": 4,
        "category": 1
      },
      {
        "id": "11",
        "name": "locality",
        "symbolSize": 35,
        "value": 100,
        "category": 1
      },
      {
        "id": "12",
        "name": "sublocality",
        "symbolSize": 30,
        "value": 6.742859,
        "category": 1
      },
      {
        "id": "13",
        "name": "sublocality_level_1",
        "symbolSize": 20,
        "value": 4,
        "category": 1
      },
      {
        "id": "14",
        "name": "sublocality_level_2",
        "symbolSize":20,
        "value": 4,
        "category": 1
      },
      {
        "id": "15",
        "name": "sublocality_level_3",
        "symbolSize": 20,
        "value": 4,
        "category": 1
      },
      {
        "id": "16",
        "name": "sublocality_level_4",
        "symbolSize": 20,
        "value": 25.942856,
        "category": 2
      },
      {
        "id": "17",
        "name": "sublocality_level_5",
        "symbolSize": 20,
        "value": 20.457146,
        "category": 2
      },
      {
        "id": "18",
        "name": "neighborhood",
        "symbolSize": 35,
        "value": 20.457146,
        "category": 2
      },
      {
        "id": "19",
        "name": "premise",
        "symbolSize": 35,
        "value": 20.457146,
        "category": 2
      },
      {
        "id": "20",
        "name": "subpremise",
        "symbolSize": 30,
        "value": 20.457146,
        "category": 2
      },
      {
        "id": "21",
        "name": "plus_code",
        "symbolSize": 35,
        "value": 20.457146,
        "category": 2
      },
      {
        "id": "22",
        "name": "postal_code",
        "symbolSize": 35,
        "value": 20.457146,
        "category": 2
      },
      {
        "id": "23",
        "name": "natural_feature",
        "symbolSize": 35,
        "value": 42.4,
        "category": 2
      },
      {
        "id": "24",
        "name": "airport",
        "symbolSize": 35,
        "value": 31.428574,
        "category": 7
      },
      {
        "id": "25",
        "name": "park",
        "symbolSize": 35,
        "value": 45.142853,
        "category": 7
      },
      {
        "id": "26",
        "name": "point_of_interest",
        "symbolSize": 35,
        "value": 31.428574,
        "category": 6
      },
      {
        "id": "27",
        "name": "floor",
        "symbolSize": 30,
        "value": 47.88571,
        "category": 7
      },
      {
        "id": "28",
        "name": "establishment",
        "symbolSize":30,
        "value": 12.228573,
        "category": 4
      },
      {
        "id": "29",
        "name": "landmark",
        "symbolSize": 30,
        "value": 23.2,
        "category": 3
      },
      {
        "id": "30",
        "name": "parking",
        "symbolSize": 30,
        "value": 6.742859,
        "category": 2
      },
      {
        "id": "31",
        "name": "post_box",
        "symbolSize": 30,
        "value": 12.228573,
        "category": 2
      },
      {
        "id": "32",
        "name": "room",
        "symbolSize": 30,
        "value": 4,
        "category": 1
      },
      {
        "id": "33",
        "name": "street_number",
        "symbolSize": 30,
        "value": 6.742859,
        "category": 1
      },
      {
        "id": "34",
        "name": "bus_station",
        "symbolSize": 30,
        "value": 17.714287,
        "category": 3
      },
      {
        "id": "35",
        "name": "train_station",
        "symbolSize": 30,
        "value": 17.714287,
        "category": 3
      },
      {
        "id": "36",
        "name": "transit_station",
        "symbolSize": 30,
        "value": 17.714287,
        "category": 3
      }
    ],
    "links": [
      {
        "source": "1",
        "target": "0"
      }
    ],
    "categories": [
      {
        "name": "类目0"
      },
      {
        "name": "类目1"
      },
      {
        "name": "类目2"
      },
      {
        "name": "类目3"
      }
    ]
  }
